ek/__init__.py
ek-0.0.6.dist-info/licenses/LICENSE
ek-0.0.6.dist-info/METADATA
ek-0.0.6.dist-info/WHEEL
ek-0.0.6.dist-info/top_level.txt
ek-0.0.6.dist-info/RECORD
