Metadata-Version: 2.4
Name: ek
Version: 0.0.6
Summary: K-means clustering with weights
Home-page: https://github.com/t-c-w/ek
Author: Thor Whalen
License: apache-2.0
Platform: any
License-File: LICENSE
Dynamic: license-file
